traductoregc/__init__.py
traductoregc/matematicas/__init__.py
traductoregc/matematicas/basico.py
traductoregc-0.0.0.dist-info/WHEEL
traductoregc-0.0.0.dist-info/METADATA
traductoregc-0.0.0.dist-info/RECORD
